plate_bending.cp313-win_amd64.pyd
plate_bending_cpp.cp313-win_amd64.pyd
plate_bending_cpp-0.1.dist-info/METADATA
plate_bending_cpp-0.1.dist-info/WHEEL
plate_bending_cpp-0.1.dist-info/top_level.txt
plate_bending_cpp-0.1.dist-info/RECORD
